scrollart/__init__.py
scrollart/__main__.py
scrollart-0.2.1.dist-info/METADATA
scrollart-0.2.1.dist-info/WHEEL
scrollart-0.2.1.dist-info/entry_points.txt
scrollart-0.2.1.dist-info/top_level.txt
scrollart-0.2.1.dist-info/RECORD
