Metadata-Version: 2.4
Name: scrollart
Version: 0.2.1
Summary: Scroll art is moving ASCII art produced by stdout text printed from a loop, "animated" as the text scrolls up the terminal.
Author: Al Sweigart
Classifier: Programming Language :: Python
Classifier: Programming Language :: Python :: 3
Requires-Python: >=3.2
